{
  "openapi": "3.0.4",
  "info": {
    "title": "FluentCRM API",
    "description": "Complete REST API documentation for FluentCRM — a self-hosted email marketing and CRM plugin for WordPress.",
    "version": "1.0.0"
  },
  "servers": [
    {
      "url": "https://{website}/wp-json/fluent-crm/v2",
      "description": "Your WordPress website",
      "variables": {
        "website": {
          "default": "YourWebsite.com",
          "description": "Your WordPress website domain (without https://)"
        }
      }
    }
  ],
  "security": [
    {
      "ApplicationPasswords": []
    }
  ],
  "paths": {
    "/subscribers/{id}/send-double-optin": {
      "post": {
        "operationId": "sendContactDoubleOptin",
        "summary": "POST Send Contact Double Opt-in",
        "description": "Send a double opt-in confirmation email to a contact. The contact should not already be in `subscribed` status.",
        "tags": [
          "Contacts"
        ],
        "security": [
          {
            "ApplicationPasswords": []
          }
        ],
        "parameters": [
          {
            "name": "id",
            "in": "path",
            "description": "The contact ID.",
            "required": true,
            "schema": {
              "type": "integer"
            }
          }
        ],
        "responses": {
          "200": {
            "description": "Double opt-in email sent successfully.",
            "content": {
              "application/json": {
                "schema": {
                  "type": "object",
                  "properties": {
                    "message": {
                      "type": "string"
                    }
                  }
                },
                "example": {
                  "message": "Double OptIn email has been sent"
                }
              }
            }
          },
          "422": {
            "description": "Contact is already subscribed.",
            "content": {
              "application/json": {
                "schema": {
                  "type": "object",
                  "properties": {
                    "message": {
                      "type": "string"
                    }
                  }
                },
                "example": {
                  "message": "Contact Already Subscribed"
                }
              }
            }
          }
        }
      }
    }
  },
  "components": {
    "schemas": {
      "Error": {
        "type": "object",
        "properties": {
          "message": {
            "type": "string",
            "description": "Human-readable error message"
          },
          "code": {
            "type": "string",
            "description": "Error code"
          },
          "data": {
            "type": "object",
            "properties": {
              "status": {
                "type": "integer",
                "description": "HTTP status code"
              }
            }
          }
        }
      }
    },
    "securitySchemes": {
      "ApplicationPasswords": {
        "type": "apiKey",
        "in": "header",
        "name": "Authorization",
        "description": "WordPress Application Passwords — use Basic auth with your WordPress username and an application password in the format: username:application_password"
      }
    }
  }
}